ape_infura/__init__.py
ape_infura/provider.py
ape_infura/py.typed
ape_infura/utils.py
ape_infura/version.py
ape_infura-0.8.2.dist-info/LICENSE
ape_infura-0.8.2.dist-info/METADATA
ape_infura-0.8.2.dist-info/WHEEL
ape_infura-0.8.2.dist-info/top_level.txt
ape_infura-0.8.2.dist-info/RECORD
