Metadata-Version: 2.1
Name: ape-infura
Version: 0.8.2
Summary: ape-infura: Infura Provider plugins for Ethereum-based networks
Home-page: https://github.com/ApeWorX/ape-infura
Author: ApeWorX Ltd.
Author-email: admin@apeworx.io
License: Apache-2.0
Keywords: ethereum
Classifier: Development Status :: 5 - Production/Stable
Classifier: Intended Audience :: Developers
Classifier: License :: OSI Approved :: MIT License
Classifier: Natural Language :: English
Classifier: Operating System :: MacOS
Classifier: Operating System :: POSIX
Classifier: Programming Language :: Python :: 3
Classifier: Programming Language :: Python :: 3.9
Classifier: Programming Language :: Python :: 3.10
Classifier: Programming Language :: Python :: 3.11
Classifier: Programming Language :: Python :: 3.12
Requires-Python: >=3.9,<4
License-File: LICENSE
Requires-Dist: eth-ape<0.9,>=0.8.1
Provides-Extra: test
Requires-Dist: pytest>=6.0; extra == "test"
Requires-Dist: pytest-xdist; extra == "test"
Requires-Dist: pytest-mock; extra == "test"
Requires-Dist: pytest-cov; extra == "test"
Requires-Dist: hypothesis<7.0,>=6.2.0; extra == "test"
Requires-Dist: ape-arbitrum; extra == "test"
Requires-Dist: ape-avalanche; extra == "test"
Requires-Dist: ape-blast; extra == "test"
Requires-Dist: ape-optimism; extra == "test"
Requires-Dist: ape-polygon; extra == "test"
Requires-Dist: websocket-client; extra == "test"
Provides-Extra: lint
Requires-Dist: black<25,>=24.10.0; extra == "lint"
Requires-Dist: mypy<2,>=1.13.0; extra == "lint"
Requires-Dist: types-setuptools; extra == "lint"
Requires-Dist: flake8<8,>=7.1.1; extra == "lint"
Requires-Dist: flake8-breakpoint<2,>=1.1.0; extra == "lint"
Requires-Dist: flake8-print<6,>=5.0.0; extra == "lint"
Requires-Dist: flake8-pydantic; extra == "lint"
Requires-Dist: flake8-type-checking; extra == "lint"
Requires-Dist: isort<6,>=5.13.2; extra == "lint"
Requires-Dist: mdformat>=0.7.19; extra == "lint"
Requires-Dist: mdformat-gfm>=0.3.5; extra == "lint"
Requires-Dist: mdformat-frontmatter>=0.4.1; extra == "lint"
Requires-Dist: mdformat-pyproject>=0.0.2; extra == "lint"
Provides-Extra: doc
Requires-Dist: myst-parser<2,>=1.0.0; extra == "doc"
Requires-Dist: sphinx-click<5,>=4.4.0; extra == "doc"
Requires-Dist: Sphinx<7,>=6.1.3; extra == "doc"
Requires-Dist: sphinx_rtd_theme<2,>=1.2.0; extra == "doc"
Requires-Dist: sphinxcontrib-napoleon>=0.7; extra == "doc"
Requires-Dist: sphinx-plausible<0.2,>=0.1.2; extra == "doc"
Provides-Extra: release
Requires-Dist: setuptools>=72.2.0; extra == "release"
Requires-Dist: setuptools-scm; extra == "release"
Requires-Dist: wheel; extra == "release"
Requires-Dist: twine; extra == "release"
Provides-Extra: dev
Requires-Dist: pytest>=6.0; extra == "dev"
Requires-Dist: pytest-xdist; extra == "dev"
Requires-Dist: pytest-mock; extra == "dev"
Requires-Dist: pytest-cov; extra == "dev"
Requires-Dist: hypothesis<7.0,>=6.2.0; extra == "dev"
Requires-Dist: ape-arbitrum; extra == "dev"
Requires-Dist: ape-avalanche; extra == "dev"
Requires-Dist: ape-blast; extra == "dev"
Requires-Dist: ape-optimism; extra == "dev"
Requires-Dist: ape-polygon; extra == "dev"
Requires-Dist: websocket-client; extra == "dev"
Requires-Dist: black<25,>=24.10.0; extra == "dev"
Requires-Dist: mypy<2,>=1.13.0; extra == "dev"
Requires-Dist: types-setuptools; extra == "dev"
Requires-Dist: flake8<8,>=7.1.1; extra == "dev"
Requires-Dist: flake8-breakpoint<2,>=1.1.0; extra == "dev"
Requires-Dist: flake8-print<6,>=5.0.0; extra == "dev"
Requires-Dist: flake8-pydantic; extra == "dev"
Requires-Dist: flake8-type-checking; extra == "dev"
Requires-Dist: isort<6,>=5.13.2; extra == "dev"
Requires-Dist: mdformat>=0.7.19; extra == "dev"
Requires-Dist: mdformat-gfm>=0.3.5; extra == "dev"
Requires-Dist: mdformat-frontmatter>=0.4.1; extra == "dev"
Requires-Dist: mdformat-pyproject>=0.0.2; extra == "dev"
Requires-Dist: myst-parser<2,>=1.0.0; extra == "dev"
Requires-Dist: sphinx-click<5,>=4.4.0; extra == "dev"
Requires-Dist: Sphinx<7,>=6.1.3; extra == "dev"
Requires-Dist: sphinx_rtd_theme<2,>=1.2.0; extra == "dev"
Requires-Dist: sphinxcontrib-napoleon>=0.7; extra == "dev"
Requires-Dist: sphinx-plausible<0.2,>=0.1.2; extra == "dev"
Requires-Dist: setuptools>=72.2.0; extra == "dev"
Requires-Dist: setuptools-scm; extra == "dev"
Requires-Dist: wheel; extra == "dev"
Requires-Dist: twine; extra == "dev"
Requires-Dist: commitizen; extra == "dev"
Requires-Dist: pre-commit; extra == "dev"
Requires-Dist: pytest-watch; extra == "dev"
Requires-Dist: IPython; extra == "dev"
Requires-Dist: ipdb; extra == "dev"
